SmartAITool/__init__.py
SmartAITool/core.py
SmartAITool/image.py
SmartAITool/video.py
smartaitool-0.4.1.dist-info/licenses/LICENSE
tests/__init__.py
tests/local_test.py
tests/test_core.py
smartaitool-0.4.1.dist-info/METADATA
smartaitool-0.4.1.dist-info/WHEEL
smartaitool-0.4.1.dist-info/top_level.txt
smartaitool-0.4.1.dist-info/RECORD
