Metadata-Version: 2.4
Name: SmartAITool
Version: 0.4.1
Summary: A smart AI tool package
Author-email: Your Name <mohammad.khalili1515@gmail.com>
Project-URL: Homepage, https://github.com/m15kh/SmartAITool
Project-URL: Bug Tracker, https://github.com/m15kh/SmartAITool/issues
Classifier: Programming Language :: Python :: 3
Classifier: License :: OSI Approved :: MIT License
Classifier: Operating System :: OS Independent
Requires-Python: >=3.7
License-File: LICENSE
Requires-Dist: opencv-python>=4.0.0
Requires-Dist: tqdm>=4.0.0
Dynamic: license-file
